setup_client.py
client/__init__.py
client/client3.py
client/client2/__init__.py
client/client2/add_contact.py
client/client2/database.py
client/client2/del_contact.py
client/client2/main_window.py
client/client2/main_window_conv.py
client/client2/start_dialog.py
client/client2/transport.py
client/common/__init__.py
client/common/decos.py
client/common/descrptrs.py
client/common/errors.py
client/common/metaclasses.py
client/common/utils.py
client/common/variables.py
client/logs/__init__.py
client/logs/config_client_log.py
client/logs/config_server_log.py
client/unit_tests/__init__.py
client_QT_NM.egg-info/PKG-INFO
client_QT_NM.egg-info/SOURCES.txt
client_QT_NM.egg-info/dependency_links.txt
client_QT_NM.egg-info/requires.txt
client_QT_NM.egg-info/top_level.txt
server/__init__.py
server/server3.py
server/common/__init__.py
server/common/decos.py
server/common/descrptrs.py
server/common/errors.py
server/common/metaclasses.py
server/common/utils.py
server/common/variables.py
server/logs/__init__.py
server/logs/config_client_log.py
server/logs/config_server_log.py
server/server2/__init__.py
server/server2/add_user.py
server/server2/config_window.py
server/server2/core.py
server/server2/database.py
server/server2/main_window.py
server/server2/remove_user.py
server/server2/stat_window.py
server/unit_tests/__init__.py