Metadata-Version: 1.0
Name: client-QT-NM
Version: 0.0.1
Summary: client
Home-page: UNKNOWN
Author: Mamicheva Natalya
Author-email: mamicheva.natalya@yandex.ru
License: UNKNOWN
Platform: UNKNOWN
